{"cameraMode":{"drawMode":0,"name":"Shaded","section":"Shading Mode"},"sceneLighting":true,"audioPlay":false,"sceneViewState":{"showFog":true,"showMaterialUpdate":false,"showSkybox":true,"showFlares":true,"showImageEffects":true,"showParticleSystems":true},"in2DMode":false,"pivot":{"x":1.6444272994995118,"y":1.7771148681640626,"z":-2.3961405754089357},"rotation":{"x":-0.1309923380613327,"y":0.5970132350921631,"z":-0.09960094094276428,"w":-0.7851741313934326},"size":3.2965619564056398,"orthographic":false}